group_remote/__init__.py
group_remote/groups_remote.py
group_remote-0.0.120.dist-info/METADATA
group_remote-0.0.120.dist-info/WHEEL
group_remote-0.0.120.dist-info/top_level.txt
group_remote-0.0.120.dist-info/RECORD
