Metadata-Version: 2.1
Name: group-remote
Version: 0.0.120
Summary: PyPI Package for Circles Group-Remote Python
Home-page: https://github.com/circles-zone/group-remote-python-package
Author: Circles
Author-email: info@circlez.ai
Classifier: Programming Language :: Python :: 3
Classifier: License :: Other/Proprietary License
Classifier: Operating System :: OS Independent
Requires-Dist: requests
Requires-Dist: logger-local
Requires-Dist: url-remote
Requires-Dist: user-context-remote
Requires-Dist: python-sdk-remote
Requires-Dist: language-remote
